Workbook

Sheet KPI_SummaryKPI_x0009_Value
A1: KPI | B1: Value
A2: Total Orders | B2: =COUNTA(Daily_Deliveries!A2:A1000) -> 180
A3: Total Revenue | B3: =SUM(Revenue_Details!G2:G1000) -> 45220
A4: Total Cost | B4: =SUM(Cost_Details!I2:I1000) -> 43920
A5: Total Profit | B5: =B3-B4 -> 1300
A6: Average Cost per Order | B6: =B4/B2 -> 244
A7: On-Time Delivery % | B7: =COUNTIF(Daily_Deliveries!K2:K1000,"Completed")/B2 -> 0.3
A8: Average Delivery Time (hrs) | B8: =AVERAGE(Daily_Deliveries!J2:J1000) -> 3.7052222

Sheet Sheet3
A3: Row Labels | B3: Count of Order_ID
A4: Belfast | B4: 18
A5: Birmingham | B5: 15
A6: Bristol | B6: 12
A7: Cardiff | B7: 17
A8: Edinburgh | B8: 25
A9: Glasgow | B9: 12
A10: Leeds | B10: 21
A11: Liverpool | B11: 18
A12: London | B12: 26
A13: Manchester | B13: 16
A14: (blank)
A15: Grand Total | B15: 180

Sheet Daily_Deliveries
A1: Date | B1: Order_ID | C1: City | D1: Region | E1: Service_Type | F1: Vehicle_Type | G1: Fuel_Type | H1: Distance_km | I1: Load_Type | J1: Delivery_Time_hr | K1: Delivery_Status | L1: Driver_ID
A2: 45742 | B2: O0001 | C2: Edinburgh | D2: Scotland | E2: Same-Day Delivery | F2: Small Truck | G2: Diesel | H2: 142 | I2: Heavy | J2: 3.25 | K2: Delayed | L2: D015
A3: 45729 | B3: O0002 | C3: Belfast | D3: Northern Ireland | E3: Parcel Delivery | F3: Pickup | G3: Petrol | H3: 48 | I3: Medium | J3: 5.69 | K3: Delayed | L3: D014
A4: 45707 | B4: O0003 | C4: Glasgow | D4: Scotland | E4: Same-Day Delivery | F4: Motorcycle | G4: Petrol | H4: 163 | I4: Heavy | J4: 2.09 | K4: Cancelled | L4: D014
A5: 45723 | B5: O0004 | C5: Edinburgh | D5: Scotland | E5: Parcel Delivery | F5: Motorcycle | G5: Petrol | H5: 110 | I5: Heavy | J5: 3.21 | K5: Completed | L5: D014
A6: 45721 | B6: O0005 | C6: London | D6: England | E6: Office Shifting | F6: Motorcycle | G6: Petrol | H6: 95 | I6: Heavy | J6: 6.22 | K6: Cancelled | L6: D002
A7: 45687 | B7: O0006 | C7: Liverpool | D7: England | E7: Same-Day Delivery | F7: Medium Truck | G7: Diesel | H7: 134 | I7: Heavy | J7: 5.84 | K7: Delayed | L7: D005
A8: 45721 | B8: O0007 | C8: Cardiff | D8: Wales | E8: Parcel Delivery | F8: Medium Truck | G8: Diesel | H8: 38 | I8: Medium | J8: 5.03 | K8: Completed | L8: D011
A9: 45736 | B9: O0008 | C9: Glasgow | D9: Scotland | E9: House Shifting | F9: Motorcycle | G9: Petrol | H9: 6 | I9: Light | J9: 5.09 | K9: Completed | L9: D004
A10: 45721 | B10: O0009 | C10: Birmingham | D10: England | E10: Fragile Items Delivery | F10: Luton Van | G10: Diesel | H10: 71 | I10: Medium | J10: 1.41 | K10: Delayed | L10: D004
A11: 45669 | B11: O0010 | C11: Manchester | D11: England | E11: Fragile Items Delivery | F11: Luton Van | G11: Diesel | H11: 100 | I11: Heavy | J11: 3.63 | K11: Completed | L11: D009
A12: 45707 | B12: O0011 | C12: Manchester | D12: England | E12: Same-Day Delivery | F12: Small Truck | G12: Diesel | H12: 163 | I12: Heavy | J12: 1.44 | K12: Cancelled | L12: D007
A13: 45711 | B13: O0012 | C13: Leeds | D13: England | E13: House Shifting | F13: Small Truck | G13: Diesel | H13: 64 | I13: Medium | J13: 2.69 | K13: Delayed | L13: D007
... A181: 45668 | B181: O0180 | C181: Birmingham | D181: England | E181: Parcel Delivery | F181: Motorcycle | G181: Petrol | H181: 133 | I181: Heavy | J181: 5.54 | K181: Cancelled | L181: D006

Sheet Cost_Details
A1: Order_ID | B1: Fuel_Cost | C1: Driver_Wage | D1: Helper_Wage | E1: Maintenance | F1: Toll | G1: Parking | H1: Other_Cost | I1: Total_Cost
A2: O0001 | B2: 88 | C2: 149 | D2: 23 | E2: 11 | F2: 15 | G2: 16 | H2: 10 | I2: =SUM(B2:H2) -> 312
A3: O0002 | B3: 40 | C3: 65 | D3: 45 | E3: 27 | F3: 23 | G3: 15 | H3: 15 | I3: =SUM(B3:H3) -> 230
A4: O0003 | B4: 60 | C4: 54 | D4: 42 | E4: 21 | F4: 15 | G4: 6 | H4: 4 | I4: =SUM(B4:H4) -> 202
A5: O0004 | B5: 116 | C5: 72 | D5: 28 | E5: 21 | F5: 11 | G5: 17 | H5: 9 | I5: =SUM(B5:H5) -> 274
A6: O0005 | B6: 74 | C6: 137 | D6: 27 | E6: 21 | F6: 12 | G6: 14 | H6: 4 | I6: =SUM(B6:H6) -> 289
A7: O0006 | B7: 91 | C7: 51 | D7: 37 | E7: 40 | F7: 5 | G7: 7 | H7: 10 | I7: =SUM(B7:H7) -> 241
A8: O0007 | B8: 21 | C8: 62 | D8: 34 | E8: 7 | F8: 2 | G8: 1 | H8: 5 | I8: =SUM(B8:H8) -> 132
A9: O0008 | B9: 97 | C9: 140 | D9: 27 | E9: 21 | F9: 18 | G9: 16 | H9: 15 | I9: =SUM(B9:H9) -> 334
A10: O0009 | B10: 63 | C10: 76 | D10: 39 | E10: 7 | F10: 5 | G10: 11 | H10: 9 | I10: =SUM(B10:H10) -> 210
A11: O0010 | B11: 72 | C11: 119 | D11: 33 | E11: 17 | F11: 14 | G11: 11 | H11: 0 | I11: =SUM(B11:H11) -> 266
A12: O0011 | B12: 49 | C12: 66 | D12: 3 | E12: 29 | F12: 0 | G12: 16 | H12: 14 | I12: =SUM(B12:H12) -> 177
A13: O0012 | B13: 61 | C13: 131 | D13: 18 | E13: 27 | F13: 6 | G13: 3 | H13: 0 | I13: =SUM(B13:H13) -> 246
... A181: O0180 | B181: 84 | C181: 116 | D181: 8 | E181: 15 | F181: 21 | G181: 1 | H181: 15 | I181: =SUM(B181:H181) -> 260

Sheet Sheet4

Sheet Revenue_Details
A1: Order_ID | B1: Base_Charge | C1: Distance_Charge | D1: Load_Charge | E1: Urgency_Charge | F1: Discount | G1: Net_Revenue
A2: O0001 | B2: 127 | C2: 69 | D2: 29 | E2: 20 | F2: 0 | G2: =SUM(B2:E2)-F2 -> 245
A3: O0002 | B3: 76 | C3: 93 | D3: 63 | E3: 40 | F3: 0 | G3: =SUM(B3:E3)-F3 -> 272
A4: O0003 | B4: 145 | C4: 70 | D4: 14 | E4: 0 | F4: 20 | G4: =SUM(B4:E4)-F4 -> 209
A5: O0004 | B5: 200 | C5: 111 | D5: 27 | E5: 0 | F5: 0 | G5: =SUM(B5:E5)-F5 -> 338
A6: O0005 | B6: 108 | C6: 39 | D6: 24 | E6: 0 | F6: 0 | G6: =SUM(B6:E6)-F6 -> 171
A7: O0006 | B7: 188 | C7: 27 | D7: 68 | E7: 20 | F7: 10 | G7: =SUM(B7:E7)-F7 -> 293
A8: O0007 | B8: 82 | C8: 100 | D8: 24 | E8: 0 | F8: 0 | G8: =SUM(B8:E8)-F8 -> 206
A9: O0008 | B9: 154 | C9: 45 | D9: 32 | E9: 0 | F9: 20 | G9: =SUM(B9:E9)-F9 -> 211
A10: O0009 | B10: 106 | C10: 115 | D10: 51 | E10: 0 | F10: 10 | G10: =SUM(B10:E10)-F10 -> 262
A11: O0010 | B11: 106 | C11: 86 | D11: 61 | E11: 40 | F11: 10 | G11: =SUM(B11:E11)-F11 -> 283
A12: O0011 | B12: 191 | C12: 97 | D12: 26 | E12: 40 | F12: 0 | G12: =SUM(B12:E12)-F12 -> 354
A13: O0012 | B13: 164 | C13: 37 | D13: 11 | E13: 40 | F13: 0 | G13: =SUM(B13:E13)-F13 -> 252
... A181: O0180 | B181: 166 | C181: 119 | D181: 76 | E181: 20 | F181: 20 | G181: =SUM(B181:E181)-F181 -> 361

Sheet Vehicle_Master
A1: Vehicle_ID | B1: Vehicle_Type | C1: Fuel_Type | D1: Ownership | E1: City | F1: Capacity_kg
A2: V001 | B2: Small Truck | C2: Diesel | D2: Company Owned | E2: Cardiff | F2: 1200
A3: V002 | B3: Luton Van | C3: Diesel | D3: Rented | E3: Bristol | F3: 2000
A4: V003 | B4: Motorcycle | C4: Petrol | D4: Leased | E4: Glasgow | F4: 1200
A5: V004 | B5: Van | C5: Diesel | D5: Rented | E5: Glasgow | F5: 3500
A6: V005 | B6: Motorcycle | C6: Petrol | D6: Rented | E6: Belfast | F6: 1200
A7: V006 | B7: Luton Van | C7: Diesel | D7: Leased | E7: Leeds | F7: 2000
A8: V007 | B8: Pickup | C8: Petrol | D8: Company Owned | E8: Belfast | F8: 3500
A9: V008 | B9: Medium Truck | C9: Diesel | D9: Rented | E9: Glasgow | F9: 1200
A10: V009 | B10: Small Truck | C10: Diesel | D10: Company Owned | E10: Liverpool | F10: 800
A11: V010 | B11: Luton Van | C11: Diesel | D11: Rented | E11: Cardiff | F11: 800
A12: V011 | B12: Motorcycle | C12: Petrol | D12: Leased | E12: Cardiff | F12: 1200
A13: V012 | B13: Medium Truck | C13: Diesel | D13: Rented | E13: Bristol | F13: 800
... A21: V020 | B21: Van | C21: Diesel | D21: Leased | E21: London | F21: 800

Sheet Driver_Master
A1: Driver_ID | B1: Driver_Type | C1: City | D1: Rating
A2: D001 | B2: Full-Time | C2: Leeds | D2: 5
A3: D002 | B3: Contract | C3: Liverpool | D3: 4
A4: D003 | B4: Part-Time | C4: Cardiff | D4: 5
A5: D004 | B5: Part-Time | C5: Leeds | D5: 3
A6: D005 | B6: Full-Time | C6: Glasgow | D6: 5
A7: D006 | B7: Contract | C7: Edinburgh | D7: 3
A8: D007 | B8: Full-Time | C8: Edinburgh | D8: 5
A9: D008 | B9: Full-Time | C9: Manchester | D9: 5
A10: D009 | B10: Full-Time | C10: Cardiff | D10: 3
A11: D010 | B11: Full-Time | C11: Edinburgh | D11: 5
A12: D011 | B12: Part-Time | C12: Liverpool | D12: 3
A13: D012 | B13: Part-Time | C13: London | D13: 3
... A16: D015 | B16: Full-Time | C16: Leeds | D16: 4

Sheet Master_Lists
A1: Service_Type | B1: Vehicle_Type | C1: Fuel_Type | D1: Delivery_Status | E1: Load_Type
A2: Parcel Delivery | B2: Van | C2: Diesel | D2: Completed | E2: Light
A3: House Shifting | B3: Luton Van | C3: Petrol | D3: Delayed | E3: Medium
A4: Office Shifting | B4: Small Truck | C4: Electric | D4: Cancelled | E4: Heavy
A5: Furniture Moving | B5: Medium Truck | C5: Hybrid | D5: Returned
A6: Fragile Items Delivery | B6: Large Truck | D6: Rescheduled
A7: Same-Day Delivery | B7: Pickup
B8: Motorcycle
